ssh_distributed/__init__.py
ssh_distributed/base.py
ssh_distributed/create_tunnel.sh
ssh_distributed/delete_directory_from_hosts.sh
ssh_distributed/download_from_hosts.sh
ssh_distributed/kill_tmux_session_on_host.sh
ssh_distributed/rsync_file.sh
ssh_distributed/run_on_host.sh
ssh_distributed/upload_to_hosts.sh
ssh_distributed-0.2.2.dist-info/METADATA
ssh_distributed-0.2.2.dist-info/WHEEL
ssh_distributed-0.2.2.dist-info/top_level.txt
ssh_distributed-0.2.2.dist-info/RECORD
