Metadata-Version: 2.1
Name: ssh-distributed
Version: 0.2.2
Summary: Microlib for managing distributed computations using ssh.
Author-email: Hristo Vrigazov <hvrigazov@gmail.com>
Project-URL: Homepage, https://github.com/microlib-org/utils_microlibs
Classifier: License :: OSI Approved :: MIT License
Classifier: Programming Language :: Python
Classifier: Programming Language :: Python :: 3
Requires-Python: >=3.8
Provides-Extra: dev
Requires-Dist: pytest ; extra == 'dev'
Requires-Dist: tqdm ; extra == 'dev'
